mass_ts/__init__.py
mass_ts/_mass2_batch.py
mass_ts/_mass_ts.py
mass_ts/_top_k.py
mass_ts/core.py
mass_ts-0.1.4.dist-info/AUTHORS.rst
mass_ts-0.1.4.dist-info/LICENSE
mass_ts-0.1.4.dist-info/METADATA
mass_ts-0.1.4.dist-info/WHEEL
mass_ts-0.1.4.dist-info/top_level.txt
mass_ts-0.1.4.dist-info/RECORD
