Metadata-Version: 2.1
Name: mass-ts
Version: 0.1.4
Summary: MASS (Mueen's Algorithm for Similarity Search)
Home-page: https://github.com/matrix-profile-foundation/mass_ts
Author: Tyler Marrs
Author-email: tylerwmarrs@gmail.com
License: Apache Software License 2.0
Keywords: mass_ts
Platform: UNKNOWN
Classifier: Development Status :: 2 - Pre-Alpha
Classifier: Intended Audience :: Developers
Classifier: License :: OSI Approved :: Apache Software License
Classifier: Natural Language :: English
Classifier: Programming Language :: Python :: 2
Classifier: Programming Language :: Python :: 2.7
Classifier: Programming Language :: Python :: 3
Classifier: Programming Language :: Python :: 3.4
Classifier: Programming Language :: Python :: 3.5
Classifier: Programming Language :: Python :: 3.6
Classifier: Programming Language :: Python :: 3.7
Requires-Dist: numpy
Provides-Extra: gpu
Requires-Dist: cupy-cuda101 (==6.2.0) ; extra == 'gpu'
